<?xml version="1.0" encoding="UTF-8"?>
<METADATA>
	<FIELD>
	  <FIELDNAME>cod_barra</FIELDNAME>
	  <EDITABLE/>
	  <VALIDATIONRULE>MANDATORY</VALIDATIONRULE>
	</FIELD>

	<FIELD>
	  <FIELDNAME>tip_barra</FIELDNAME>
	  <DOMAINREADER>
	    <DRTYPE>db</DRTYPE>
	    <DRDBSCHEMA>inventario_dominios</DRDBSCHEMA>
	    <DRDBTABLE>tip_barra</DRDBTABLE>
	    <DRDBCOLUMNALIAS>key</DRDBCOLUMNALIAS>
	    <DRDBCOLUMNVALUE>key</DRDBCOLUMNVALUE>
	    <DRADDVOIDVALUE>true</DRADDVOIDVALUE>
	   </DOMAINREADER>
	</FIELD>

   <FIELD>
    <FIELDNAME>altitude</FIELDNAME>
	<VALIDATIONRULE>DOUBLE_POSITIVE</VALIDATIONRULE>
   </FIELD>

   	<FIELD>
	  <FIELDNAME>provincia</FIELDNAME>
	  <DOMAINREADER>
	    <DRTYPE>db</DRTYPE>
	    <DRDBSCHEMA>inventario_dominios</DRDBSCHEMA>
	    <DRDBTABLE>provincia</DRDBTABLE>
	    <DRDBCOLUMNALIAS>key</DRDBCOLUMNALIAS>
	    <DRDBCOLUMNVALUE>key</DRDBCOLUMNVALUE>
	    <DRADDVOIDVALUE>true</DRADDVOIDVALUE>
	  </DOMAINREADER>
	</FIELD>

	<FIELD>
	  <FIELDNAME>distrito</FIELDNAME>
	  <DOMAINREADER>
	    <DRTYPE>db</DRTYPE>
	    <DRDBSCHEMA>inventario_dominios</DRDBSCHEMA>
	    <DRDBTABLE>distrito</DRDBTABLE>
	    <DRDBCOLUMNALIAS>key</DRDBCOLUMNALIAS>
	    <DRDBCOLUMNVALUE>key</DRDBCOLUMNVALUE>
	    <DRDBFOREIGNKEY>parent</DRDBFOREIGNKEY>
	    <DRADDVOIDVALUE>true</DRADDVOIDVALUE>
	  </DOMAINREADER>
	</FIELD>

	<FIELD>
	  <FIELDNAME>posto_adm</FIELDNAME>
	  <DOMAINREADER>
	    <DRTYPE>db</DRTYPE>
	    <DRDBSCHEMA>inventario_dominios</DRDBSCHEMA>
	    <DRDBTABLE>posto</DRDBTABLE>
	    <DRDBCOLUMNALIAS>key</DRDBCOLUMNALIAS>
	    <DRDBCOLUMNVALUE>key</DRDBCOLUMNVALUE>
	    <DRDBFOREIGNKEY>parent</DRDBFOREIGNKEY>
	    <DRADDVOIDVALUE>true</DRADDVOIDVALUE>
	  </DOMAINREADER>
	</FIELD>

	<FIELD>
	  <FIELDNAME>bacia</FIELDNAME>
	  <DOMAINREADER>
	    <DRTYPE>db</DRTYPE>
	    <DRDBSCHEMA>inventario_dominios</DRDBSCHEMA>
	    <DRDBTABLE>bacia</DRDBTABLE>
	    <DRDBCOLUMNALIAS>key</DRDBCOLUMNALIAS>
	    <DRDBCOLUMNVALUE>key</DRDBCOLUMNVALUE>
	    <DRDBFOREIGNKEY>parent</DRDBFOREIGNKEY>
	    <DRADDVOIDVALUE>true</DRADDVOIDVALUE>
	  </DOMAINREADER>
	</FIELD>
	
	<FIELD>
	  <FIELDNAME>subacia</FIELDNAME>
	  <DOMAINREADER>
	    <DRTYPE>db</DRTYPE>
	    <DRDBSCHEMA>inventario_dominios</DRDBSCHEMA>
	    <DRDBTABLE>subacia</DRDBTABLE>
	    <DRDBCOLUMNALIAS>key</DRDBCOLUMNALIAS>
	    <DRDBCOLUMNVALUE>key</DRDBCOLUMNVALUE>
	    <DRDBFOREIGNKEY>parent</DRDBFOREIGNKEY>
	    <DRADDVOIDVALUE>true</DRADDVOIDVALUE>
	  </DOMAINREADER>
	</FIELD>

	<FIELD>
	  <FIELDNAME>estado</FIELDNAME>
	  <DOMAINREADER>
	    <DRTYPE>db</DRTYPE>
	    <DRDBSCHEMA>inventario_dominios</DRDBSCHEMA>
	    <DRDBTABLE>estado_ampliado</DRDBTABLE>
	    <DRDBCOLUMNALIAS>key</DRDBCOLUMNALIAS>
	    <DRDBCOLUMNVALUE>key</DRDBCOLUMNVALUE>
	    <DRADDVOIDVALUE>true</DRADDVOIDVALUE>
	   </DOMAINREADER>
	</FIELD>

  <FIELD>
    <FIELDNAME>ano_const</FIELDNAME>
	<VALIDATIONRULE>INTEGER_POSITIVE</VALIDATIONRULE>
   </FIELD>

	<FIELD>
	  <FIELDNAME>gestao</FIELDNAME>
	  <DOMAINREADER>
	    <DRTYPE>db</DRTYPE>
	    <DRDBSCHEMA>inventario_dominios</DRDBSCHEMA>
	    <DRDBTABLE>gestao</DRDBTABLE>
	    <DRDBCOLUMNALIAS>key</DRDBCOLUMNALIAS>
	    <DRDBCOLUMNVALUE>key</DRDBCOLUMNVALUE>
	    <DRADDVOIDVALUE>true</DRADDVOIDVALUE>
	   </DOMAINREADER>
	</FIELD>

  <FIELD>
    <FIELDNAME>capacidad</FIELDNAME>
	<VALIDATIONRULE>INTEGER_POSITIVE</VALIDATIONRULE>
   </FIELD>

  <FIELD>
    <FIELDNAME>comprimen</FIELDNAME>
	<VALIDATIONRULE>INTEGER_POSITIVE</VALIDATIONRULE>
   </FIELD>

  <FIELD>
    <FIELDNAME>npa</FIELDNAME>
	<VALIDATIONRULE>INTEGER_POSITIVE</VALIDATIONRULE>
   </FIELD>

  <FIELD>
    <FIELDNAME>h_altitud</FIELDNAME>
	<VALIDATIONRULE>DOUBLE_POSITIVE</VALIDATIONRULE>
   </FIELD>

     <FIELD>
    <FIELDNAME>n_inspec</FIELDNAME>
	<VALIDATIONRULE>INTEGER_POSITIVE</VALIDATIONRULE>
   </FIELD>

	<FIELD>
	  <FIELDNAME>fiab_info</FIELDNAME>
	  <DOMAINREADER>
	    <DRTYPE>db</DRTYPE>
	    <DRDBSCHEMA>inventario_dominios</DRDBSCHEMA>
	    <DRDBTABLE>fiab_info</DRDBTABLE>
	    <DRDBCOLUMNALIAS>key</DRDBCOLUMNALIAS>
	    <DRDBCOLUMNVALUE>key</DRDBCOLUMNVALUE>
	    <DRADDVOIDVALUE>true</DRADDVOIDVALUE>
	   </DOMAINREADER>
	</FIELD>

</METADATA>
