<?xml version="1.0" encoding="UTF-8"?>
<METADATA>
	<FIELD>
		<FIELDNAME>cadastro</FIELDNAME>
		<NONEDITABLE/>
		<VALIDATIONRULE>MANDATORY</VALIDATIONRULE>
	</FIELD>
	
	<FIELD>
		<FIELDNAME>data_lit</FIELDNAME>
		<VALIDATIONRULE>DATE</VALIDATIONRULE>
	</FIELD>
	
	<FIELD>
	  <FIELDNAME>tipo_cama</FIELDNAME>
	  <DOMAINREADER>
	    <DRTYPE>db</DRTYPE>
	    <DRDBSCHEMA>inventario_dominios</DRDBSCHEMA>
	    <DRDBTABLE>tipo_cama</DRDBTABLE>
	    <DRDBCOLUMNALIAS>key</DRDBCOLUMNALIAS>
	    <DRDBCOLUMNVALUE>key</DRDBCOLUMNVALUE>
	    <DRADDVOIDVALUE>true</DRADDVOIDVALUE>
	  </DOMAINREADER>
	</FIELD>
	
	<FIELD>
	  <FIELDNAME>tipo_aqui</FIELDNAME>
	  <DOMAINREADER>
	    <DRTYPE>db</DRTYPE>
	    <DRDBSCHEMA>inventario_dominios</DRDBSCHEMA>
	    <DRDBTABLE>tipo_aqui</DRDBTABLE>
	    <DRDBCOLUMNALIAS>key</DRDBCOLUMNALIAS>
	    <DRDBCOLUMNVALUE>key</DRDBCOLUMNVALUE>
	    <DRADDVOIDVALUE>true</DRADDVOIDVALUE>
	  </DOMAINREADER>
	</FIELD>
	
	<FIELD>
		<FIELDNAME>q_aquifer</FIELDNAME>
		<VALIDATIONRULE>DOUBLE_POSITIVE</VALIDATIONRULE>
	</FIELD>
	
	<FIELD>
		<FIELDNAME>conductiv</FIELDNAME>
		<VALIDATIONRULE>DOUBLE_POSITIVE</VALIDATIONRULE>
	</FIELD>
	
</METADATA>
